autoCal/__init__.py
autoCal/helperConverters.py
autoCal/motorCalculations.py
autoCal/speedCalculations.py
autoCal/unitConverters.py
autoCal-0.0.6.dist-info/LICENSE
autoCal-0.0.6.dist-info/METADATA
autoCal-0.0.6.dist-info/WHEEL
autoCal-0.0.6.dist-info/top_level.txt
autoCal-0.0.6.dist-info/RECORD
