Metadata-Version: 2.1
Name: autoCal
Version: 0.0.6
Summary: Collection of automotive calculations
Author: GladsonThomas
Author-email: <gladson.thomas.official@gmail.com>
Keywords: python,calculations,automotive,EV,BLDC
Classifier: Development Status :: 1 - Planning
Classifier: Intended Audience :: Developers
Classifier: Programming Language :: Python :: 3
Classifier: Operating System :: Unix
Classifier: Operating System :: MacOS :: MacOS X
Classifier: Operating System :: Microsoft :: Windows
License-File: LICENSE
